comux/__init__.py
comux/__main__.py
comux/terminate.py
comux/consumer/__init__.py
comux/ctx/__init__.py
comux/db/__init__.py
comux/logger/__init__.py
comux/producer/__init__.py
comux/structures/__init__.py
comux-0.2.0.dist-info/LICENSE
comux-0.2.0.dist-info/METADATA
comux-0.2.0.dist-info/WHEEL
comux-0.2.0.dist-info/top_level.txt
comux-0.2.0.dist-info/RECORD
