Metadata-Version: 2.1
Name: comux
Version: 0.2.0
Summary: Video stream flow: Kafka-Comsumer, LibAV-Decoder, Kafka-Producer
Author-email: dev_molavi <dev.molavi@gmail.com>
Project-URL: Homepage, https://github.com/HamedMolavi/comux
Classifier: Programming Language :: Python :: 3
Classifier: License :: OSI Approved :: MIT License
Classifier: Operating System :: OS Independent
Requires-Python: >=3.10
License-File: LICENSE
